supriya/__init__.py
supriya/_version.py
supriya/conversions.py
supriya/enums.py
supriya/exceptions.py
supriya/io.py
supriya/py.typed
supriya/sclang.py
supriya/scsynth.py
supriya/soundfiles.py
supriya/typing.py
supriya/utils.py
supriya/clocks/__init__.py
supriya/clocks/asynchronous.py
supriya/clocks/core.py
supriya/clocks/offline.py
supriya/clocks/threaded.py
supriya/contexts/__init__.py
supriya/contexts/allocators.py
supriya/contexts/core.py
supriya/contexts/entities.py
supriya/contexts/nonrealtime.py
supriya/contexts/realtime.py
supriya/contexts/requests.py
supriya/contexts/responses.py
supriya/contexts/scopes.py
supriya/contexts/shm.cp312-win_arm64.pyd
supriya/contexts/shm.cpp
supriya/contexts/shm.pxd
supriya/contexts/shm.pyi
supriya/contexts/shm.pyx
supriya/ext/__init__.py
supriya/ext/book.py
supriya/ext/ipython.py
supriya/ext/mypy.py
supriya/osc/__init__.py
supriya/osc/asynchronous.py
supriya/osc/messages.py
supriya/osc/protocols.py
supriya/osc/threaded.py
supriya/osc/utils.py
supriya/patterns/__init__.py
supriya/patterns/eventpatterns.py
supriya/patterns/events.py
supriya/patterns/noise.py
supriya/patterns/patterns.py
supriya/patterns/players.py
supriya/patterns/structure.py
supriya/samples/birds-01.wav
supriya/samples/birds-02.wav
supriya/samples/birds-03.wav
supriya/samples/birds-04.wav
supriya/samples/birds-05.wav
supriya/samples/birds-06.wav
supriya/samples/birds-07.wav
supriya/samples/birds-08.wav
supriya/samples/birds-09.wav
supriya/samples/pulse_44100sr_16bit_octo.wav
supriya/samples/sine_1320hz_44100sr_16bit_mono_1s.wav
supriya/samples/sine_1760hz_44100sr_16bit_mono_1s.wav
supriya/samples/sine_440hz_44100sr_16bit_mono.wav
supriya/samples/sine_440hz_44100sr_16bit_mono_1s.wav
supriya/samples/sine_440hz_44100sr_16bit_octo.wav
supriya/samples/sine_880hz_44100sr_16bit_mono_1s.wav
supriya/ugens/__init__.py
supriya/ugens/basic.py
supriya/ugens/beq.py
supriya/ugens/bufio.py
supriya/ugens/chaos.py
supriya/ugens/compilers.py
supriya/ugens/convolution.py
supriya-25.9b1.dist-info/licenses/LICENSE
supriya-25.9b1.dist-info/METADATA
supriya-25.9b1.dist-info/WHEEL
supriya-25.9b1.dist-info/top_level.txt
supriya-25.9b1.dist-info/RECORD
