Metadata-Version: 2.4
Name: supriya
Version: 25.9b1
Summary: A Python API for SuperCollider
Author-email: Joséphine Wolf Oberholtzer <josephine.wolf.oberholtzer@gmail.com>
License: MIT
Project-URL: homepage, https://github.com/supriya-project/supriya
Project-URL: documentation, https://supriya-project.github.io/supriya
Project-URL: repository, https://github.com/supriya-project/supriya
Keywords: audio,dsp,music composition,scsynth,supercollider,synthesis
Classifier: Framework :: AsyncIO
Classifier: Intended Audience :: Developers
Classifier: License :: OSI Approved :: MIT License
Classifier: Natural Language :: English
Classifier: Operating System :: MacOS
Classifier: Operating System :: POSIX
Classifier: Operating System :: Microsoft :: Windows
Classifier: Programming Language :: Python :: 3.10
Classifier: Programming Language :: Python :: 3.11
Classifier: Programming Language :: Python :: 3.12
Classifier: Programming Language :: Python :: 3.13
Classifier: Topic :: Artistic Software
Classifier: Topic :: Multimedia :: Sound/Audio
Classifier: Topic :: Multimedia :: Sound/Audio :: Analysis
Classifier: Topic :: Multimedia :: Sound/Audio :: Sound Synthesis
Requires-Python: >=3.10
License-File: LICENSE
Requires-Dist: backports.strenum; python_version < "3.11"
Requires-Dist: platformdirs>=4.0.0
Requires-Dist: psutil
Requires-Dist: uqbar>=0.9.6
Provides-Extra: docs
Requires-Dist: supriya[examples]; extra == "docs"
Requires-Dist: jupyterlab; extra == "docs"
Requires-Dist: jupyterlab-rise; extra == "docs"
Requires-Dist: librosa; extra == "docs"
Requires-Dist: matplotlib; extra == "docs"
Requires-Dist: mypy; extra == "docs"
Requires-Dist: soxr; extra == "docs"
Requires-Dist: sphinx; extra == "docs"
Requires-Dist: sphinx-immaterial; extra == "docs"
Requires-Dist: sphinx-toolbox; extra == "docs"
Requires-Dist: sphinxext-opengraph; extra == "docs"
Requires-Dist: standard-aifc; python_version >= "3.13" and extra == "docs"
Requires-Dist: standard-sunau; python_version >= "3.13" and extra == "docs"
Provides-Extra: examples
Requires-Dist: pynput; extra == "examples"
Requires-Dist: python-rtmidi; extra == "examples"
Provides-Extra: test
Requires-Dist: IPython; extra == "test"
Requires-Dist: librosa; extra == "test"
Requires-Dist: lxml; extra == "test"
Requires-Dist: matplotlib; extra == "test"
Requires-Dist: mypy; extra == "test"
Requires-Dist: pytest; extra == "test"
Requires-Dist: pytest-asyncio; extra == "test"
Requires-Dist: pytest-cov; extra == "test"
Requires-Dist: pytest-lazy-fixtures; extra == "test"
Requires-Dist: pytest-mock; extra == "test"
Requires-Dist: pytest-rerunfailures; extra == "test"
Requires-Dist: ruff; extra == "test"
Requires-Dist: standard-aifc; python_version >= "3.13" and extra == "test"
Requires-Dist: standard-sunau; python_version >= "3.13" and extra == "test"
Requires-Dist: types-PyYAML; extra == "test"
Requires-Dist: types-docutils; extra == "test"
Requires-Dist: types-psutil; extra == "test"
Requires-Dist: types-pynput; extra == "test"
Dynamic: license-file
